fast_agent/__init__.py
fast_agent/fastagent.py
fast_agent/functodict.py
py_fast_agent-0.2.0.dist-info/LICENSE
py_fast_agent-0.2.0.dist-info/METADATA
py_fast_agent-0.2.0.dist-info/WHEEL
py_fast_agent-0.2.0.dist-info/top_level.txt
py_fast_agent-0.2.0.dist-info/RECORD
